rlogger/__init__.py
rlogger/rlogger.py
rlogger-3.0.dist-info/LICENSE
rlogger-3.0.dist-info/METADATA
rlogger-3.0.dist-info/WHEEL
rlogger-3.0.dist-info/top_level.txt
rlogger-3.0.dist-info/RECORD
