Metadata-Version: 2.1
Name: rlogger
Version: 3.0
Summary: An Python logger
Home-page: UNKNOWN
Author: rivergold
Author-email: jinghe.rivergold@gmail.com
License: MIT
Platform: UNKNOWN
